chrome_rdp_wrapper/__init__.py
chrome_rdp_wrapper-0.0.2.dist-info/METADATA
chrome_rdp_wrapper-0.0.2.dist-info/WHEEL
chrome_rdp_wrapper-0.0.2.dist-info/top_level.txt
chrome_rdp_wrapper-0.0.2.dist-info/RECORD
