Metadata-Version: 2.1
Name: chrome-rdp-wrapper
Version: 0.0.2
Summary: Chrome RDP Wrapper
Home-page: https://github.com/48723247842/ChromeRDPWrapper
Author: 7435171
Author-email: 48723247842@protonmail.com
License: UNKNOWN
Platform: UNKNOWN
Classifier: Programming Language :: Python :: 3
Classifier: License :: OSI Approved :: MIT License
Classifier: Operating System :: OS Independent
Requires-Python: >=3.8
Requires-Dist: XDoToolWrapper (>=0.0.4)
Requires-Dist: requests (>=2.22.0)
Requires-Dist: websocket-client (>=0.57.0)
